random_information_generator/Info.py
random_information_generator/__init__.py
random_information_generator-1.1.dist-info/LICENSE
random_information_generator-1.1.dist-info/METADATA
random_information_generator-1.1.dist-info/WHEEL
random_information_generator-1.1.dist-info/entry_points.txt
random_information_generator-1.1.dist-info/top_level.txt
random_information_generator-1.1.dist-info/RECORD
