Metadata-Version: 2.1
Name: random-information-generator
Version: 1.1
Summary: This tool is made to generate Randomized information. All addresses generated ARE REAL they are all grabbed off 'https://openaddresses.io'
Home-page: https://github.com/FatherVonTayvious/Random-Information-Generator
Download-URL: https://github.com/FatherVonTayvious/Random-Information-Generator/releases
Author: TheArchitect#8198
Maintainer: ona li toki e jan Epiphany tawa mi
License: GPL-3.0-or-later
Keywords: random information generator,random_information_generator,random,generator,openaddresses,random-profile,color,terminal,colorama,password
Platform: Any
Classifier: Development Status :: 6 - Mature
Classifier: Environment :: Console
Classifier: Intended Audience :: End Users/Desktop
Classifier: Natural Language :: English
Classifier: Operating System :: OS Independent
Classifier: Programming Language :: Python :: 3
Classifier: Topic :: Utilities
License-File: LICENSE
Requires-Dist: colorama
Requires-Dist: random-address
Requires-Dist: random-profile
